metapatch/__init__.py
metapatch/base.py
metapatch/circuit_generation/__init__.py
metapatch/circuit_generation/formatting.py
metapatch/circuit_generation/models.py
metapatch/circuit_generation/parsing.py
metapatch/circuit_generation/templates/aliases.j2
metapatch/circuit_generation/templates/category.j2
metapatch/circuit_generation/templates/init.j2
metapatch/circuit_generation/writer.py
metapatch/circuits/README.md
metapatch/circuits/__init__.py
metapatch/circuits/aliases.py
metapatch/circuits/base.py
metapatch/circuits/circuit_types.py
metapatch/circuits/clock.py
metapatch/circuits/cv.py
metapatch/circuits/deprecated.py
metapatch/circuits/logic.py
metapatch/circuits/midi.py
metapatch/circuits/modulation.py
metapatch/circuits/other.py
metapatch/circuits/pitch.py
metapatch/circuits/sequencing.py
metapatch/circuits/ui.py
metapatch/cli_util.py
metapatch/factory/__init__.py
metapatch/factory/boilerplate.py
metapatch/factory/context.py
metapatch/factory/formatting.py
metapatch/factory/patch_factory.py
metapatch/factory/patch_parser.py
metapatch/metapatch.py
metapatch/options.py
metapatch/py.typed
metapatch/utils.py
droid_metapatch-3.0.2.dist-info/WHEEL
droid_metapatch-3.0.2.dist-info/entry_points.txt
droid_metapatch-3.0.2.dist-info/METADATA
droid_metapatch-3.0.2.dist-info/RECORD
