Metadata-Version: 2.4
Name: droid-metapatch
Version: 3.0.2
Summary: DROID patch generator
Author: Allan Eising
Author-email: Allan Eising <allan@eising.dk>
License-Expression: GPL-3.0-only
Requires-Dist: jinja2>=3.1.4,<4
Requires-Dist: pydantic>=2.11.7
Requires-Python: >=3.12
Project-URL: Documentation, https://eising.github.io/droid-metapatch
Project-URL: Repository, https://github.com/Eising/droid-metapatch
